pybol/Manifest.py
pybol/__init__.py
pybol-0.2.1.dist-info/METADATA
pybol-0.2.1.dist-info/WHEEL
pybol-0.2.1.dist-info/top_level.txt
pybol-0.2.1.dist-info/zip-safe
pybol-0.2.1.dist-info/RECORD
